ensemble_analyzer/__init__.py
ensemble_analyzer/__main__.py
ensemble_analyzer/clustering.py
ensemble_analyzer/constants.py
ensemble_analyzer/ensemble_io.py
ensemble_analyzer/graph.py
ensemble_analyzer/io_utils.py
ensemble_analyzer/launch.py
ensemble_analyzer/parser_arguments.py
ensemble_analyzer/parser_parameter.py
ensemble_analyzer/rrho.py
ensemble_analyzer/title.py
ensemble_analyzer/_calculators/__init__.py
ensemble_analyzer/_calculators/_gaussian.py
ensemble_analyzer/_calculators/_orca.py
ensemble_analyzer/_calculators/base.py
ensemble_analyzer/_clustering/__init__.py
ensemble_analyzer/_clustering/cluster_config.py
ensemble_analyzer/_clustering/cluster_manager.py
ensemble_analyzer/_conformer/__init__.py
ensemble_analyzer/_conformer/conformer.py
ensemble_analyzer/_conformer/energy_data.py
ensemble_analyzer/_conformer/spectral_data.py
ensemble_analyzer/_logger/__init__.py
ensemble_analyzer/_logger/create_log.py
ensemble_analyzer/_logger/formatter.py
ensemble_analyzer/_logger/logger.py
ensemble_analyzer/_managers/__init__.py
ensemble_analyzer/_managers/calculation_config.py
ensemble_analyzer/_managers/calculation_executor.py
ensemble_analyzer/_managers/calculator_orchestration.py
ensemble_analyzer/_managers/checkpoint_manager.py
ensemble_analyzer/_managers/protocol_executor.py
ensemble_analyzer/_managers/protocol_manager.py
ensemble_analyzer/_managers/pruning_manager.py
ensemble_analyzer/_parsers/__init__.py
ensemble_analyzer/_parsers/_gaussian.py
ensemble_analyzer/_parsers/_orca.py
ensemble_analyzer/_parsers/base.py
ensemble_analyzer/_protocol/__init__.py
ensemble_analyzer/_protocol/protocol.py
ensemble_analyzer/_protocol/solvent.py
ensemble_analyzer/_spectral/__init__.py
ensemble_analyzer/_spectral/base.py
ensemble_analyzer/_spectral/comp_electronic.py
ensemble_analyzer/_spectral/comp_vibronic.py
ensemble_analyzer/_spectral/compare.py
ensemble_analyzer/_spectral/experimental.py
ensemble_analyzer/_spectral/graph_default.py
ensemble_analyzer/cli/__init__.py
ensemble_analyzer-1.dist-info/licenses/LICENSE
ensemble_analyzer-1.dist-info/METADATA
ensemble_analyzer-1.dist-info/WHEEL
ensemble_analyzer-1.dist-info/entry_points.txt
ensemble_analyzer-1.dist-info/top_level.txt
ensemble_analyzer-1.dist-info/RECORD
