Metadata-Version: 2.4
Name: ensemble-analyzer
Version: 1
Summary: Automatic Refinement of Conformational Ensemble
Author-email: Andrea Pellegrini <andrea.pellegrini15@unibo.it>, Paolo Righi <paolo.righi@unibo.it>, Andrea Mazzanti <andrea.mazzanti@unibo.it>, Michele Mancinelli <michele.mancinelli@unibo.it>
Maintainer-email: Andrea Pellegrini <andrea.pellegrini15@unibo.it>, Paolo Righi <paolo.righi@unibo.it>
License: MIT
Project-URL: Homepage, https://github.com/andre-cloud/ensemble_analyzer
Project-URL: Documentation, https://enan.readthedocs.io/en/latest/
Keywords: computational-chemistry,conformational-analysis,ensemble-refinement,automatization,ase,quantum-chemistry
Classifier: Development Status :: 5 - Production/Stable
Classifier: Intended Audience :: Science/Research
Classifier: Intended Audience :: Developers
Classifier: Topic :: Scientific/Engineering :: Chemistry
Classifier: Topic :: Scientific/Engineering :: Physics
Classifier: License :: OSI Approved :: MIT License
Classifier: Programming Language :: Python :: 3
Classifier: Programming Language :: Python :: 3.11
Classifier: Programming Language :: Python :: 3.12
Classifier: Programming Language :: Python :: 3.13
Classifier: Programming Language :: Python :: 3 :: Only
Classifier: Operating System :: OS Independent
Classifier: Typing :: Typed
Requires-Python: >=3.11
License-File: LICENSE
Requires-Dist: numpy>=2.2.0
Requires-Dist: scipy>=1.16.3
Requires-Dist: matplotlib>=3.10.7
Requires-Dist: scikit-learn>=1.7.2
Requires-Dist: ase>=3.24.0
Requires-Dist: numba>=0.61.2
Requires-Dist: tabulate>=0.9.0
Requires-Dist: InquirerPy>=0.3.4
Dynamic: license-file
